README.md
setup.cfg
setup.py
vsyspy/__init__.py
vsyspy/account.py
vsyspy/chain.py
vsyspy/contract.py
vsyspy/crypto.py
vsyspy/deser.py
vsyspy/errors.py
vsyspy/setting.py
vsyspy/version.py
vsyspy/vsyspy
vsyspy/words.py
vsyspy/wrapper.py
vsyspy.egg-info/PKG-INFO
vsyspy.egg-info/SOURCES.txt
vsyspy.egg-info/dependency_links.txt
vsyspy.egg-info/not-zip-safe
vsyspy.egg-info/requires.txt
vsyspy.egg-info/top_level.txt