Metadata-Version: 1.2
Name: vsyspy
Version: 2020.3
Summary: A Python api wrapper for VSYS network.
Home-page: https://github.com/Icermli/vsyspy
Author: Icerm
Author-email: haohan@v.systems
License: MIT
Download-URL: https://github.com/Icermli/vsyspy/archive/version@2020.3.tar.gz
Keywords: api wrapper
Platform: UNKNOWN
Classifier: Development Status :: 5 - Production/Stable
Classifier: Intended Audience :: Developers
Classifier: License :: OSI Approved :: MIT License
Classifier: Programming Language :: Python
Classifier: Programming Language :: Python :: 3.7
Classifier: Programming Language :: Python :: 3.8
Requires-Python: >=3.0
